drifter_functions.py
setup.cfg
setup.py
package_test.egg-info/PKG-INFO
package_test.egg-info/SOURCES.txt
package_test.egg-info/dependency_links.txt
package_test.egg-info/top_level.txt