Metadata-Version: 1.0
Name: package-test
Version: 0.1.1
Summary: that is a test 
Home-page: UNKNOWN
Author: huanxin
Author-email: xhx509@gmail.com
License: no
Keywords: test
Platform: UNKNOWN
